yt_thumbnail_creator/__init__.py
yt_thumbnail_creator/assests_gen.py
yt_thumbnail_creator/yt_thumb_gen.py
yt_thumbnail_creator/llm/prompt.jinja2
yt_thumbnail_creator-0.1.1.dist-info/METADATA
yt_thumbnail_creator-0.1.1.dist-info/WHEEL
yt_thumbnail_creator-0.1.1.dist-info/top_level.txt
yt_thumbnail_creator-0.1.1.dist-info/RECORD
