Metadata-Version: 2.1
Name: yt_thumbnail_creator
Version: 0.1.1
Summary: Generating Thumbnail for everyone
Author: S Likhith Sai
Author-email: semalalikithsai@gmail.com
Keywords: python,video,youtube,thumbnail,photos,stable-diffusion
Classifier: Development Status :: 3 - Alpha
Classifier: Intended Audience :: Developers
Classifier: Programming Language :: Python :: 3
Classifier: Operating System :: OS Independent
Classifier: License :: OSI Approved :: MIT License
Classifier: Topic :: Multimedia :: Graphics
Requires-Python: >=3.7
Requires-Dist: groq
Requires-Dist: gradio-client
Requires-Dist: Pillow
Requires-Dist: rembg
Requires-Dist: colorama
